netilion_api/__init__.py
netilion_api/api_client.py
netilion_api/configuration.py
netilion_api/rest.py
netilion_api/api/__init__.py
netilion_api/api/api_key_api.py
netilion_api/api/api_subscription_api.py
netilion_api/api/asset_api.py
netilion_api/api/asset_health_condition_api.py
netilion_api/api/asset_status_api.py
netilion_api/api/attachment_api.py
netilion_api/api/bill_of_material_api.py
netilion_api/api/client_application_api.py
netilion_api/api/company_api.py
netilion_api/api/customer_api.py
netilion_api/api/delivery_api.py
netilion_api/api/delivery_status_api.py
netilion_api/api/document_api.py
netilion_api/api/document_category_api.py
netilion_api/api/document_classification_api.py
netilion_api/api/document_status_api.py
netilion_api/api/event_api.py
netilion_api/api/event_status_api.py
netilion_api/api/event_type_api.py
netilion_api/api/health_condition_api.py
netilion_api/api/health_condition_cause_api.py
netilion_api/api/health_condition_interval_api.py
netilion_api/api/health_condition_remedy_api.py
netilion_api/api/instrumentation_api.py
netilion_api/api/instrumentation_health_condition_api.py
netilion_api/api/instrumentation_status_api.py
netilion_api/api/instrumentation_type_api.py
netilion_api/api/lookup_api.py
netilion_api/api/node_api.py
netilion_api/api/node_type_api.py
netilion_api/api/permission_api.py
netilion_api/api/permission_request_api.py
netilion_api/api/product_api.py
netilion_api/api/product_category_api.py
netilion_api/api/product_health_condition_api.py
netilion_api/api/product_identifier_api.py
netilion_api/api/product_status_api.py
netilion_api/api/purchase_order_api.py
netilion_api/api/purchase_order_status_api.py
netilion_api/api/quotation_api.py
netilion_api/api/quotation_status_api.py
netilion_api/api/request_for_quotation_api.py
netilion_api/api/request_for_quotation_status_api.py
netilion_api/api/search_api.py
netilion_api/api/software_api.py
netilion_api/api/software_attachment_api.py
netilion_api/api/spare_part_api.py
netilion_api-1.2.4.dist-info/licenses/LICENSE
netilion_api-1.2.4.dist-info/METADATA
netilion_api-1.2.4.dist-info/WHEEL
netilion_api-1.2.4.dist-info/top_level.txt
netilion_api-1.2.4.dist-info/RECORD
